{
  "_fv": 23,
  "_type": "tool",
  "definition": {
    "renderType": 0,
    "texture": "iceshank",
    "customModelName": "Normal",
    "name": "Hero's Icicle",
    "specialInfo": [],
    "creativeTab": {
      "value": "COMBAT"
    },
    "toolType": "Sword",
    "harvestLevel": 2,
    "efficiency": 6.0,
    "attackSpeed": 1.3,
    "enchantability": 0,
    "damageVsEntity": 6.0,
    "usageCount": 400,
    "blocksAffected": [],
    "hasGlow": false,
    "repairItems": [],
    "immuneToFire": true,
    "stayInGridWhenCrafting": false,
    "damageOnCrafting": false,
    "onEntityHitWith": {
      "name": "IceRelicSwordLivingEntityIsHitWithTool"
    }
  }
}